moquag
setup.py
moquag/__init__.py
moquag/main.py
moquag.egg-info/PKG-INFO
moquag.egg-info/SOURCES.txt
moquag.egg-info/dependency_links.txt
moquag.egg-info/not-zip-safe
moquag.egg-info/requires.txt
moquag.egg-info/top_level.txt