Metadata-Version: 1.0
Name: moquag
Version: 0.244
Summary: Mongo query aggregator using bulk operators
Home-page: https://github.com/quantumgraph/mongo-query-aggregator
Author: QuantumGraph
Author-email: contact@quantumgraph.com
License: MIT
Platform: UNKNOWN
